example_package_abdulmughni/__init__.py
example_package_abdulmughni/example.py
example_package_abdulmughni-0.1.0.dist-info/LICENSE.txt
example_package_abdulmughni-0.1.0.dist-info/METADATA
example_package_abdulmughni-0.1.0.dist-info/WHEEL
example_package_abdulmughni-0.1.0.dist-info/top_level.txt
example_package_abdulmughni-0.1.0.dist-info/RECORD
