Metadata-Version: 2.1
Name: example-package-abdulmughni
Version: 0.1.0
Summary: An example Python package
Home-page: UNKNOWN
Author: Abdul Mughni
Author-email: abdulmughni100@gmail.com
License: UNKNOWN
Platform: UNKNOWN
Classifier: Programming Language :: Python :: 3
Classifier: License :: OSI Approved :: MIT License
Classifier: Operating System :: OS Independent
Requires-Python: >=3.6
Requires-Dist: numpy
Requires-Dist: tensorflow
